journeyman/__init__.py
journeyman_nn-0.0.1.dist-info/LICENSE
journeyman_nn-0.0.1.dist-info/METADATA
journeyman_nn-0.0.1.dist-info/WHEEL
journeyman_nn-0.0.1.dist-info/top_level.txt
journeyman_nn-0.0.1.dist-info/RECORD
